LICENSE
README.rst
setup.py
bin/run_galprime
galprime/__init__.py
galprime-old/__init__.py
galprime-old/bgsub.py
galprime-old/binning.py
galprime-old/config.py
galprime-old/cutouts.py
galprime-old/extraction.py
galprime-old/masking.py
galprime-old/modeling.py
galprime-old/sims.py
galprime-old/isophote_l/__init__.py
galprime-old/isophote_l/ellipse.py
galprime-old/isophote_l/fitter.py
galprime-old/isophote_l/geometry.py
galprime-old/isophote_l/harmonics.py
galprime-old/isophote_l/integrator.py
galprime-old/isophote_l/isophote.py
galprime-old/isophote_l/model.py
galprime-old/isophote_l/sample.py
galprime-old/isophotes/__init__.py
galprime-old/isophotes/harmonics.py
galprime-old/isophotes/sampling.py
galprime-old/models/__init__.py
galprime-old/models/backgrounds.py
galprime-old/models/galaxies.py
galprime-old/models/kdes.py
galprime-old/models/psfs.py
galprime-old/models/tests/__init__.py
galprime-old/models/tests/test_bgmodels.py
galprime-old/models/tests/test_galaxies.py
galprime-old/plotting/__init__.py
galprime-old/plotting/general_plots.py
galprime-old/plotting/matrix_plots.py
galprime-old/plotting/plotting_utils.py
galprime-old/plotting/verification_plots.py
galprime-old/plotting/tests/__init__.py
galprime-old/plotting/tests/test_plotting.py
galprime-old/tests/__init__.py
galprime-old/tests/test_backgrounds.py
galprime-old/tests/test_binning.py
galprime-old/tests/test_config.py
galprime-old/tests/test_cutouts.py
galprime-old/tests/test_extraction.py
galprime-old/tests/test_masking.py
galprime-old/tests/test_sims.py
galprime-old/utils/__init__.py
galprime-old/utils/cosmology.py
galprime-old/utils/fluxes.py
galprime-old/utils/generators.py
galprime-old/utils/handling.py
galprime-old/utils/misc.py
galprime-old/utils/tests/__init__.py
galprime.egg-info/PKG-INFO
galprime.egg-info/SOURCES.txt
galprime.egg-info/dependency_links.txt
galprime.egg-info/requires.txt
galprime.egg-info/top_level.txt
galprime/analysis/__init__.py
galprime/analysis/fluxes.py
galprime/core/__init__.py
galprime/core/bgsub.py
galprime/core/binning.py
galprime/core/config.py
galprime/core/cutouts.py
galprime/core/extraction.py
galprime/core/masking.py
