Metadata-Version: 2.1
Name: galprime
Version: 3.0.0
Summary: GALaxy Profile Recovery from Images of Model Emission
Home-page: https://github.com/hsouch/galprime
Author: Harrison Souchereau
Author-email: harrison.souchereau@yale.edu
Classifier: Development Status :: 3 - Alpha
Classifier: Intended Audience :: Developers
Classifier: License :: OSI Approved :: MIT License
Classifier: Programming Language :: Python :: 3
Classifier: Programming Language :: Python :: 3.6
Classifier: Programming Language :: Python :: 3.7
Classifier: Programming Language :: Python :: 3.8
License-File: LICENSE
Requires-Dist: astropy>=5
Requires-Dist: photutils>=1.10
Requires-Dist: numpy>=1.26
Requires-Dist: scikit-image>=0.19
Requires-Dist: configobj
Requires-Dist: pebble
